skill_lab/__init__.py
skill_lab/__main__.py
skill_lab/cli.py
skill_lab/checks/__init__.py
skill_lab/checks/base.py
skill_lab/checks/static/__init__.py
skill_lab/checks/static/content.py
skill_lab/checks/static/description.py
skill_lab/checks/static/frontmatter.py
skill_lab/checks/static/naming.py
skill_lab/checks/static/structure.py
skill_lab/core/__init__.py
skill_lab/core/exceptions.py
skill_lab/core/models.py
skill_lab/core/registry.py
skill_lab/core/scoring.py
skill_lab/core/utils.py
skill_lab/evaluators/__init__.py
skill_lab/evaluators/static_evaluator.py
skill_lab/evaluators/trace_evaluator.py
skill_lab/parsers/__init__.py
skill_lab/parsers/skill_parser.py
skill_lab/parsers/trace_parser.py
skill_lab/reporters/__init__.py
skill_lab/reporters/console_reporter.py
skill_lab/reporters/json_reporter.py
skill_lab/runtimes/__init__.py
skill_lab/runtimes/base.py
skill_lab/runtimes/claude_runtime.py
skill_lab/runtimes/codex_runtime.py
skill_lab/tracechecks/__init__.py
skill_lab/tracechecks/registry.py
skill_lab/tracechecks/trace_check_loader.py
skill_lab/tracechecks/handlers/__init__.py
skill_lab/tracechecks/handlers/base.py
skill_lab/tracechecks/handlers/command_presence.py
skill_lab/tracechecks/handlers/efficiency.py
skill_lab/tracechecks/handlers/event_sequence.py
skill_lab/tracechecks/handlers/file_creation.py
skill_lab/tracechecks/handlers/loop_detection.py
skill_lab/triggers/__init__.py
skill_lab/triggers/test_loader.py
skill_lab/triggers/trace_analyzer.py
skill_lab/triggers/trigger_evaluator.py
skill_lab-0.1.0.dist-info/licenses/LICENSE
skill_lab-0.1.0.dist-info/METADATA
skill_lab-0.1.0.dist-info/WHEEL
skill_lab-0.1.0.dist-info/entry_points.txt
skill_lab-0.1.0.dist-info/top_level.txt
skill_lab-0.1.0.dist-info/RECORD
