Metadata-Version: 2.4
Name: skill-lab
Version: 0.1.0
Summary: A Python CLI tool for evaluating agent skills through static analysis and quality checks
Author-email: Eddie Hu <eddiehu0314@gmail.com>
License-Expression: MIT
Project-URL: Homepage, https://github.com/8ddieHu0314/Skill-Lab
Project-URL: Documentation, https://github.com/8ddieHu0314/Skill-Lab#readme
Project-URL: Repository, https://github.com/8ddieHu0314/Skill-Lab
Project-URL: Issues, https://github.com/8ddieHu0314/Skill-Lab/issues
Project-URL: Releases, https://github.com/8ddieHu0314/Skill-Lab/releases
Keywords: agent,skills,evaluation,cli,static-analysis,quality,SKILL.md,ai-agents
Classifier: Development Status :: 4 - Beta
Classifier: Environment :: Console
Classifier: Intended Audience :: Developers
Classifier: Operating System :: OS Independent
Classifier: Programming Language :: Python :: 3
Classifier: Programming Language :: Python :: 3.10
Classifier: Programming Language :: Python :: 3.11
Classifier: Programming Language :: Python :: 3.12
Classifier: Programming Language :: Python :: 3.13
Classifier: Topic :: Software Development :: Quality Assurance
Classifier: Topic :: Software Development :: Testing
Classifier: Typing :: Typed
Requires-Python: >=3.10
License-File: LICENSE
Requires-Dist: typer>=0.9.0
Requires-Dist: rich>=13.0.0
Requires-Dist: pyyaml>=6.0
Provides-Extra: dev
Requires-Dist: pytest>=7.0; extra == "dev"
Requires-Dist: pytest-cov>=4.0; extra == "dev"
Requires-Dist: mypy>=1.0; extra == "dev"
Requires-Dist: ruff>=0.1.0; extra == "dev"
Dynamic: license-file
